splayout/__init__.py
splayout/adjointmethod/__init__.py
splayout/adjointmethod/adjointmultitoopt.py
splayout/adjointmethod/adjointshapeopt.py
splayout/adjointmethod/adjointtopologyopt.py
splayout/adjointmethod/scalabletoregion3d.py
splayout/adjointmethod/shaperegion2d.py
splayout/adjointmethod/shaperegion3d.py
splayout/adjointmethod/topologyregion2d.py
splayout/adjointmethod/topologyregion3d.py
splayout/algorithms/__init__.py
splayout/algorithms/binarybatalgorithm.py
splayout/algorithms/binarygeneticalgorithm.py
splayout/algorithms/binaryparticleswarmalgorithm.py
splayout/algorithms/directbinarysearchalgorithm.py
splayout/algorithms/particleswarmalgorithm.py
splayout/components/AEMDgrating.py
splayout/components/__init__.py
splayout/components/bend.py
splayout/components/doubleconnector.py
splayout/components/filledpattern.py
splayout/components/microring.py
splayout/components/pixelsregion.py
splayout/components/polygon.py
splayout/components/quarbend.py
splayout/components/sbend.py
splayout/components/selfdefinecomponent.py
splayout/components/simpleasymmetricdirectionalcoupler.py
splayout/components/slowlyvaryingtaper.py
splayout/components/taper.py
splayout/components/text.py
splayout/components/waveguide.py
splayout/lumericalcommun/__init__.py
splayout/lumericalcommun/fdtdapi.py
splayout/lumericalcommun/modeapi.py
splayout/utils/__init__.py
splayout/utils/utils.py
splayout-0.5.16.dist-info/licenses/LICENSE
splayout-0.5.16.dist-info/METADATA
splayout-0.5.16.dist-info/WHEEL
splayout-0.5.16.dist-info/top_level.txt
splayout-0.5.16.dist-info/RECORD
