Metadata-Version: 2.4
Name: SPLayout
Version: 0.5.16
Summary: Silicon Photonics Design Tools for GDSII Files.
Home-page: https://github.com/Hideousmon/SPLayout
Author: Zhenyu ZHAO
Author-email: mailtozyzhao@163.com
License-File: LICENSE
Requires-Dist: gdspy
Requires-Dist: numpy
Requires-Dist: scipy
Dynamic: author
Dynamic: author-email
Dynamic: description
Dynamic: home-page
Dynamic: license-file
Dynamic: requires-dist
Dynamic: summary
